datequarter/__init__.py
datequarter/quarter.py
datetime_quarter-1.0.3.dist-info/LICENSE
datetime_quarter-1.0.3.dist-info/METADATA
datetime_quarter-1.0.3.dist-info/WHEEL
datetime_quarter-1.0.3.dist-info/top_level.txt
datetime_quarter-1.0.3.dist-info/RECORD
