Metadata-Version: 2.1
Name: datetime-quarter
Version: 1.0.3
Summary: Simple and lightweight quarter support for python datetime
Home-page: https://github.com/BetaS/datetime-quarter
Author: BetaS
Author-email: thou1999@gmail.com
License: UNKNOWN
Platform: UNKNOWN
Classifier: Programming Language :: Python :: 3
Classifier: License :: OSI Approved :: MIT License
